{"timestamp": "Fri Mar  4 15:11:08 2022", "loosers": [{"ticker": "OBMP", "name": "Theralink Technologies, Inc.", "change": "-37.10%"}, {"ticker": "TIIAY", "name": "Telecom Italia S.p.A.", "change": "-16.31%"}, {"ticker": "UNCRY", "name": "UniCredit S.p.A.", "change": "-13.98%"}, {"ticker": "HCM", "name": "HUTCHMED (China) Limited", "change": "-12.68%"}, {"ticker": "VZIO", "name": "VIZIO Holding Corp.", "change": "-11.82%"}, {"ticker": "ITVPF", "name": "ITV plc", "change": "-11.21%"}, {"ticker": "CPNG", "name": "Coupang, Inc.", "change": "-9.68%"}, {"ticker": "NPSNY", "name": "Naspers Limited", "change": "-10.14%"}, {"ticker": "SCGLY", "name": "Soci\u00e9t\u00e9 G\u00e9n\u00e9rale Soci\u00e9t\u00e9 anonyme", "change": "-9.69%"}, {"ticker": "ALSMY", "name": "Alstom SA", "change": "-9.29%"}, {"ticker": "IITSF", "name": "Intesa Sanpaolo S.p.A.", "change": "-9.92%"}, {"ticker": "CRH", "name": "CRH plc", "change": "-9.39%"}, {"ticker": "POAHY", "name": "Porsche Automobil Holding SE", "change": "-9.14%"}, {"ticker": "ING", "name": "ING Groep N.V.", "change": "-9.18%"}, {"ticker": "DB", "name": "Deutsche Bank Aktiengesellschaft", "change": "-9.09%"}, {"ticker": "SQSP", "name": "Squarespace, Inc.", "change": "-8.65%"}, {"ticker": "ISPO", "name": "Inspirato Incorporated", "change": "-9.79%"}, {"ticker": "DOCN", "name": "DigitalOcean Holdings, Inc.", "change": "-8.50%"}, {"ticker": "JDCMF", "name": "JD.com, Inc.", "change": "-8.45%"}, {"ticker": "MT", "name": "ArcelorMittal S.A.", "change": "-8.35%"}, {"ticker": "CPRI", "name": "Capri Holdings Limited", "change": "-8.32%"}, {"ticker": "STLA", "name": "Stellantis N.V.", "change": "-8.14%"}, {"ticker": "S", "name": "SentinelOne, Inc.", "change": "-8.31%"}, {"ticker": "DUFRY", "name": "Dufry AG", "change": "-7.82%"}, {"ticker": "VWAPY", "name": "Volkswagen AG", "change": "-7.85%"}]}