{"timestamp": "Thu Jul 28 15:11:25 2022", "loosers": [{"ticker": "TDOC", "name": "Teladoc Health, Inc.", "change": "-20.07%"}, {"ticker": "HAYW", "name": "Hayward Holdings, Inc.", "change": "-18.34%"}, {"ticker": "UPWK", "name": "Upwork Inc.", "change": "-17.68%"}, {"ticker": "PGY", "name": "Pagaya Technologies Ltd.", "change": "-15.79%"}, {"ticker": "FORM", "name": "FormFactor, Inc.", "change": "-15.35%"}, {"ticker": "BLCO", "name": "Bausch + Lomb Corporation", "change": "-14.50%"}, {"ticker": "FMS", "name": "Fresenius Medical Care AG & Co. KGaA", "change": "-14.76%"}, {"ticker": "CINF", "name": "Cincinnati Financial Corporation", "change": "-14.14%"}, {"ticker": "SLM", "name": "SLM Corporation", "change": "-13.68%"}, {"ticker": "PEGA", "name": "Pegasystems Inc.", "change": "-12.80%"}, {"ticker": "ACCYY", "name": "Accor SA", "change": "-12.39%"}, {"ticker": "SWK", "name": "Stanley Black & Decker, Inc.", "change": "-12.42%"}, {"ticker": "GRFS", "name": "Grifols, S.A.", "change": "-11.60%"}, {"ticker": "CNX", "name": "CNX Resources Corporation", "change": "-11.55%"}, {"ticker": "SNN", "name": "Smith & Nephew plc", "change": "-11.67%"}, {"ticker": "FSNUY", "name": "Fresenius SE & Co. KGaA", "change": "-10.09%"}, {"ticker": "CMCSA", "name": "Comcast Corporation", "change": "-9.87%"}, {"ticker": "CLBK", "name": "Columbia Financial, Inc.", "change": "-9.65%"}, {"ticker": "BAX", "name": "Baxter International Inc.", "change": "-9.35%"}, {"ticker": "OMF", "name": "OneMain Holdings, Inc.", "change": "-8.86%"}, {"ticker": "STNG", "name": "Scorpio Tankers Inc.", "change": "-8.84%"}, {"ticker": "NVCR", "name": "NovoCure Limited", "change": "-8.62%"}, {"ticker": "LUV", "name": "Southwest Airlines Co.", "change": "-8.23%"}, {"ticker": "CHTR", "name": "Charter Communications, Inc.", "change": "-8.46%"}, {"ticker": "AAFRF", "name": "Airtel Africa Plc", "change": "-8.21%"}]}