{"timestamp": "Mon Oct 10 13:53:29 2022", "loosers": [{"ticker": "FIVN", "name": "Five9, Inc.", "change": "-16.31%"}, {"ticker": "SCRYY", "name": "SCOR SE", "change": "+4.55%"}, {"ticker": "ADDDF", "name": "adidas AG", "change": "-9.52%"}, {"ticker": "BILI", "name": "Bilibili Inc.", "change": "-8.38%"}, {"ticker": "EDU", "name": "New Oriental Education & Technology Group Inc.", "change": "-6.71%"}, {"ticker": "F", "name": "Ford Motor Company", "change": "-6.72%"}, {"ticker": "LU", "name": "Lufax Holding Ltd", "change": "-6.70%"}, {"ticker": "CS", "name": "Credit Suisse Group AG", "change": "-7.11%"}, {"ticker": "CIG-C", "name": "Companhia Energ\u00e9tica de Minas Gerais", "change": "+4.36%"}, {"ticker": "UNVGY", "name": "Universal Music Group N.V.", "change": "-6.52%"}, {"ticker": "RIVN", "name": "Rivian Automotive, Inc.", "change": "-6.33%"}, {"ticker": "BZ", "name": "Kanzhun Limited", "change": "-6.73%"}, {"ticker": "TENB", "name": "Tenable Holdings, Inc.", "change": "-6.70%"}, {"ticker": "RNG", "name": "RingCentral, Inc.", "change": "-6.38%"}, {"ticker": "MNDY", "name": "monday.com Ltd.", "change": "-6.16%"}, {"ticker": "WYNN", "name": "Wynn Resorts, Limited", "change": "-6.25%"}, {"ticker": "AXTA", "name": "Axalta Coating Systems Ltd.", "change": "-5.12%"}, {"ticker": "LRCX", "name": "Lam Research Corporation", "change": "-6.09%"}, {"ticker": "HTHT", "name": "H World Group Limited", "change": "-5.45%"}, {"ticker": "TCOM", "name": "Trip.com Group Limited", "change": "-5.68%"}, {"ticker": "FUTU", "name": "Futu Holdings Limited", "change": "-6.32%"}, {"ticker": "FRLOF", "name": "Frasers Logistics & Commercial Trust", "change": "-5.58%"}, {"ticker": "BHPLF", "name": "BHP Group Limited", "change": "0.00%"}, {"ticker": "MLCO", "name": "Melco Resorts & Entertainment Limited", "change": "-7.66%"}, {"ticker": "GM", "name": "General Motors Company", "change": "-4.83%"}]}