{"timestamp": "Mon Aug 23 18:11:52 2021", "loosers": [{"ticker": "MKTW", "name": "MarketWise, Inc.", "change": "-18.16%"}, {"ticker": "SHWDY", "name": "Showa Denko K.K.", "change": "-14.50%"}, {"ticker": "TAL", "name": "TAL Education Group", "change": "-9.16%"}, {"ticker": "STOHF", "name": "Equinor ASA", "change": "-8.00%"}, {"ticker": "ZH", "name": "Zhihu Inc.", "change": "-7.16%"}, {"ticker": "GCPEF", "name": "GCL-Poly Energy Holdings Limited", "change": "-7.04%"}, {"ticker": "EDU", "name": "New Oriental Education & Technology Group Inc.", "change": "-6.59%"}, {"ticker": "PNXGF", "name": "Phoenix Group Holdings plc", "change": "-6.02%"}, {"ticker": "PHJMF", "name": "PT Hanjaya Mandala Sampoerna Tbk", "change": "-5.57%"}, {"ticker": "HEPS", "name": "D-MARKET Elektronik Hizmetler ve Ticaret Anonim Sirketi", "change": "-5.51%"}, {"ticker": "REE", "name": "REE Automotive Ltd.", "change": "-5.92%"}, {"ticker": "LZ", "name": "LegalZoom.com, Inc.", "change": "-5.36%"}, {"ticker": "OSCR", "name": "Oscar Health, Inc.", "change": "-5.30%"}, {"ticker": "VZIO", "name": "VIZIO Holding Corp.", "change": "-4.71%"}, {"ticker": "LU", "name": "Lufax Holding Ltd", "change": "-5.08%"}, {"ticker": "HIPO", "name": "Hippo Holdings Inc.", "change": "-4.76%"}, {"ticker": "SNYNF", "name": "Sanofi", "change": "-4.70%"}, {"ticker": "BODY", "name": "The Beachbody Company, Inc.", "change": "-4.04%"}, {"ticker": "DLO", "name": "DLocal Limited", "change": "-4.27%"}, {"ticker": "KNBE", "name": "KnowBe4, Inc.", "change": "-3.89%"}, {"ticker": "QFIN", "name": "360 DigiTech, Inc.", "change": "-4.24%"}, {"ticker": "KMTUF", "name": "Komatsu Ltd.", "change": "-4.01%"}, {"ticker": "FSUGY", "name": "Fortescue Metals Group Limited", "change": "-3.71%"}, {"ticker": "SPXCF", "name": "Singapore Exchange Limited", "change": "-3.63%"}, {"ticker": "ME", "name": "23andMe Holding Co.", "change": "-3.56%"}]}