{"timestamp": "Mon Nov 28 15:10:12 2022", "loosers": [{"ticker": "PSNY", "name": "Polestar Automotive Holding UK PLC", "change": "-8.13%"}, {"ticker": "PHJMF", "name": "PT Hanjaya Mandala Sampoerna Tbk", "change": "-7.42%"}, {"ticker": "APE", "name": "AMC Entertainment Holdings, Inc.", "change": "-4.97%"}, {"ticker": "PR", "name": "Permian Resources Corporation", "change": "-4.71%"}, {"ticker": "CPE", "name": "Callon Petroleum Company", "change": "-4.48%"}, {"ticker": "EURN", "name": "Euronav NV", "change": "-4.68%"}, {"ticker": "FRO", "name": "Frontline Ltd.", "change": "-4.80%"}, {"ticker": "OMCL", "name": "Omnicell, Inc.", "change": "-4.55%"}, {"ticker": "JKS", "name": "JinkoSolar Holding Co., Ltd.", "change": "-4.20%"}, {"ticker": "MUR", "name": "Murphy Oil Corporation", "change": "-4.27%"}, {"ticker": "CIVI", "name": "Civitas Resources, Inc.", "change": "-4.43%"}, {"ticker": "TDG", "name": "TransDigm Group Incorporated", "change": "-4.18%"}, {"ticker": "SGRY", "name": "Surgery Partners, Inc.", "change": "-2.97%"}, {"ticker": "EADSY", "name": "Airbus SE", "change": "-4.15%"}, {"ticker": "WSM", "name": "Williams-Sonoma, Inc.", "change": "-4.20%"}, {"ticker": "MTDR", "name": "Matador Resources Company", "change": "-4.21%"}, {"ticker": "EVA", "name": "Enviva Inc.", "change": "-4.03%"}, {"ticker": "EC", "name": "Ecopetrol S.A.", "change": "-3.93%"}, {"ticker": "INSW", "name": "International Seaways, Inc.", "change": "-4.00%"}, {"ticker": "KOS", "name": "Kosmos Energy Ltd.", "change": "-3.74%"}, {"ticker": "MGY", "name": "Magnolia Oil & Gas Corporation", "change": "-3.86%"}, {"ticker": "QS", "name": "QuantumScape Corporation", "change": "-3.84%"}, {"ticker": "ESTE", "name": "Earthstone Energy, Inc.", "change": "-3.42%"}, {"ticker": "KMT", "name": "Kennametal Inc.", "change": "-3.62%"}, {"ticker": "CRK", "name": "Comstock Resources, Inc.", "change": "-3.97%"}]}