{"timestamp": "Tue Feb 22 18:12:21 2022", "loosers": [{"ticker": "SBRCY", "name": "Sberbank of Russia", "change": "-21.56%"}, {"ticker": "TPX", "name": "Tempur Sealy International, Inc.", "change": "-19.19%"}, {"ticker": "VIAC", "name": "Paramount Global", "change": "-17.81%"}, {"ticker": "VIACA", "name": "Paramount Global", "change": "-16.31%"}, {"ticker": "SHCAY", "name": "Sharp Corporation", "change": "-15.47%"}, {"ticker": "OGZPY", "name": "Public Joint Stock Company Gazprom", "change": "-15.44%"}, {"ticker": "RLX", "name": "RLX Technology Inc.", "change": "-13.55%"}, {"ticker": "LUKOY", "name": "PJSC LUKOIL", "change": "-13.53%"}, {"ticker": "SGTZY", "name": "Surgutneftegas Public Joint Stock Company", "change": "-13.07%"}, {"ticker": "ETRN", "name": "Equitrans Midstream Corporation", "change": "-12.50%"}, {"ticker": "MPLN", "name": "MultiPlan Corporation", "change": "-10.40%"}, {"ticker": "YNDX", "name": "Yandex N.V.", "change": "-10.42%"}, {"ticker": "TUIFY", "name": "TUI AG", "change": "-10.22%"}, {"ticker": "SGTPY", "name": "Surgutneftegas Public Joint Stock Company", "change": "-7.74%"}, {"ticker": "FSNUY", "name": "Fresenius SE & Co. KGaA", "change": "-9.78%"}, {"ticker": "XNGSY", "name": "ENN Energy Holdings Limited", "change": "-9.76%"}, {"ticker": "PACB", "name": "Pacific Biosciences of California, Inc.", "change": "-9.37%"}, {"ticker": "BILI", "name": "Bilibili Inc.", "change": "-9.10%"}, {"ticker": "GCPEF", "name": "GCL-Poly Energy Holdings Limited", "change": "-9.00%"}, {"ticker": "SOFI", "name": "SoFi Technologies, Inc.", "change": "-8.91%"}, {"ticker": "PATH", "name": "UiPath Inc.", "change": "-9.01%"}, {"ticker": "HD", "name": "The Home Depot, Inc.", "change": "-9.01%"}, {"ticker": "XPEV", "name": "XPeng Inc.", "change": "-8.89%"}, {"ticker": "SWMAF", "name": "Swedish Match AB (publ)", "change": "-8.63%"}, {"ticker": "RIVN", "name": "Rivian Automotive, Inc.", "change": "-8.44%"}]}