{"timestamp": "Thu Jul 21 18:13:59 2022", "loosers": [{"ticker": "HLFFF", "name": "HelloFresh SE", "change": "-20.76%"}, {"ticker": "PGY", "name": "Pagaya Technologies Ltd.", "change": "-15.79%"}, {"ticker": "HELFY", "name": "HelloFresh SE", "change": "-14.21%"}, {"ticker": "CCL", "name": "Carnival Corporation & plc", "change": "-11.23%"}, {"ticker": "POOL", "name": "Pool Corporation", "change": "-11.06%"}, {"ticker": "UAL", "name": "United Airlines Holdings, Inc.", "change": "-10.29%"}, {"ticker": "CUK", "name": "Carnival Corporation & plc", "change": "-9.83%"}, {"ticker": "PBF", "name": "PBF Energy Inc.", "change": "-9.97%"}, {"ticker": "DFS", "name": "Discover Financial Services", "change": "-9.46%"}, {"ticker": "HP", "name": "Helmerich & Payne, Inc.", "change": "-9.33%"}, {"ticker": "RCL", "name": "Royal Caribbean Cruises Ltd.", "change": "-9.29%"}, {"ticker": "PTEN", "name": "Patterson-UTI Energy, Inc.", "change": "-8.95%"}, {"ticker": "AAL", "name": "American Airlines Group Inc.", "change": "-8.55%"}, {"ticker": "CVT", "name": "Cvent Holding Corp.", "change": "-8.07%"}, {"ticker": "NCLH", "name": "Norwegian Cruise Line Holdings Ltd.", "change": "-8.14%"}, {"ticker": "T", "name": "AT&T Inc.", "change": "-7.73%"}, {"ticker": "HAYW", "name": "Hayward Holdings, Inc.", "change": "-7.69%"}, {"ticker": "AMR", "name": "Alpha Metallurgical Resources, Inc.", "change": "-7.32%"}, {"ticker": "ENIAY", "name": "Enel Am\u00e9ricas S.A.", "change": "-6.95%"}, {"ticker": "BTU", "name": "Peabody Energy Corporation", "change": "-7.17%"}, {"ticker": "ALL", "name": "The Allstate Corporation", "change": "-6.53%"}, {"ticker": "LBRT", "name": "Liberty Energy Inc.", "change": "-6.63%"}, {"ticker": "BKR", "name": "Baker Hughes Company", "change": "-6.51%"}, {"ticker": "CPE", "name": "Callon Petroleum Company", "change": "-6.34%"}, {"ticker": "CVI", "name": "CVR Energy, Inc.", "change": "-6.29%"}]}