{"timestamp": "Thu Mar 30 17:08:29 2023", "loosers": [{"ticker": "AGL", "name": "agilon health, inc.", "change": "-13.27%"}, {"ticker": "TRMD", "name": "TORM plc", "change": "-12.52%"}, {"ticker": "NTRA", "name": "Natera, Inc.", "change": "-8.30%"}, {"ticker": "PHJMF", "name": "PT Hanjaya Mandala Sampoerna Tbk", "change": "-7.62%"}, {"ticker": "VRNT", "name": "Verint Systems Inc.", "change": "-7.56%"}, {"ticker": "BMBL", "name": "Bumble Inc.", "change": "-6.17%"}, {"ticker": "MTCH", "name": "Match Group, Inc.", "change": "-6.00%"}, {"ticker": "BBIO", "name": "BridgeBio Pharma, Inc.", "change": "-5.35%"}, {"ticker": "SCHW", "name": "The Charles Schwab Corporation", "change": "-5.26%"}, {"ticker": "MDGL", "name": "Madrigal Pharmaceuticals, Inc.", "change": "-5.06%"}, {"ticker": "NEOG", "name": "Neogen Corporation", "change": "-5.38%"}, {"ticker": "DNLI", "name": "Denali Therapeutics Inc.", "change": "-4.98%"}, {"ticker": "GRAB", "name": "Grab Holdings Limited", "change": "-4.14%"}, {"ticker": "W", "name": "Wayfair Inc.", "change": "-4.40%"}, {"ticker": "GH", "name": "Guardant Health, Inc.", "change": "-4.83%"}, {"ticker": "BPIRY", "name": "Piraeus Financial Holdings S.A.", "change": "-4.71%"}, {"ticker": "ISEE", "name": "IVERIC bio, Inc.", "change": "-4.49%"}, {"ticker": "RXDX", "name": "Prometheus Biosciences, Inc.", "change": "-4.68%"}, {"ticker": "AXSM", "name": "Axsome Therapeutics, Inc.", "change": "-4.16%"}, {"ticker": "ROKU", "name": "Roku, Inc.", "change": "-4.48%"}, {"ticker": "FRC", "name": "First Republic Bank", "change": "-3.28%"}, {"ticker": "PRTA", "name": "Prothena Corporation plc", "change": "-4.02%"}, {"ticker": "CTLT", "name": "Catalent, Inc.", "change": "-3.91%"}, {"ticker": "NEP", "name": "NextEra Energy Partners, LP", "change": "-3.68%"}, {"ticker": "ATAT", "name": "Atour Lifestyle Holdings Limited", "change": "-3.96%"}]}