{"timestamp": "Mon Jan 30 15:10:11 2023", "loosers": [{"ticker": "DADA", "name": "Dada Nexus Limited", "change": "-11.73%"}, {"ticker": "GDS", "name": "GDS Holdings Limited", "change": "-10.31%"}, {"ticker": "BILI", "name": "Bilibili Inc.", "change": "-9.38%"}, {"ticker": "HCM", "name": "HUTCHMED (China) Limited", "change": "-8.00%"}, {"ticker": "LU", "name": "Lufax Holding Ltd", "change": "-7.41%"}, {"ticker": "MOMO", "name": "Hello Group Inc.", "change": "-6.91%"}, {"ticker": "TME", "name": "Tencent Music Entertainment Group", "change": "-6.57%"}, {"ticker": "MLCO", "name": "Melco Resorts & Entertainment Limited", "change": "-6.53%"}, {"ticker": "XIACY", "name": "Xiaomi Corporation", "change": "-6.29%"}, {"ticker": "PROSY", "name": "Prosus N.V.", "change": "-6.33%"}, {"ticker": "TCEHY", "name": "Tencent Holdings Limited", "change": "-6.37%"}, {"ticker": "PDD", "name": "Pinduoduo Inc.", "change": "-5.97%"}, {"ticker": "ZNH", "name": "China Southern Airlines Company Limited", "change": "-5.91%"}, {"ticker": "YMM", "name": "Full Truck Alliance Co. Ltd.", "change": "-5.39%"}, {"ticker": "CAJ", "name": "Canon Inc.", "change": "-5.33%"}, {"ticker": "NPSNY", "name": "Naspers Limited", "change": "-5.48%"}, {"ticker": "PACB", "name": "Pacific Biosciences of California, Inc.", "change": "-5.39%"}, {"ticker": "WB", "name": "Weibo Corporation", "change": "-4.81%"}, {"ticker": "AFLYY", "name": "Air France-KLM SA", "change": "-5.16%"}, {"ticker": "VIPS", "name": "Vipshop Holdings Limited", "change": "-4.92%"}, {"ticker": "BABA", "name": "Alibaba Group Holding Limited", "change": "-4.84%"}, {"ticker": "JD", "name": "JD.com, Inc.", "change": "-4.61%"}, {"ticker": "TCOM", "name": "Trip.com Group Limited", "change": "-4.74%"}, {"ticker": "XPEV", "name": "XPeng Inc.", "change": "-4.72%"}, {"ticker": "WXXWY", "name": "WuXi Biologics (Cayman) Inc.", "change": "-4.76%"}]}