{"timestamp": "Thu May 19 20:12:21 2022", "loosers": [{"ticker": "UA", "name": "Under Armour, Inc.", "change": "-15.86%"}, {"ticker": "CSCO", "name": "Cisco Systems, Inc.", "change": "-13.73%"}, {"ticker": "UAA", "name": "Under Armour, Inc.", "change": "-11.97%"}, {"ticker": "RAZFF", "name": "Razer Inc.", "change": "-11.18%"}, {"ticker": "EXEL", "name": "Exelixis, Inc.", "change": "-10.52%"}, {"ticker": "TGOPY", "name": "3i Group plc", "change": "-9.57%"}, {"ticker": "HOG", "name": "Harley-Davidson, Inc.", "change": "-9.23%"}, {"ticker": "IIVI", "name": "II-VI Incorporated", "change": "-7.72%"}, {"ticker": "FIZZ", "name": "National Beverage Corp.", "change": "-6.93%"}, {"ticker": "BBWI", "name": "Bath & Body Works, Inc.", "change": "-6.78%"}, {"ticker": "LCII", "name": "LCI Industries", "change": "-6.69%"}, {"ticker": "CVNA", "name": "Carvana Co.", "change": "-5.79%"}, {"ticker": "MAT", "name": "Mattel, Inc.", "change": "-6.06%"}, {"ticker": "AMTD", "name": "AMTD IDEA Group", "change": "-5.99%"}, {"ticker": "CIB", "name": "Bancolombia S.A.", "change": "-5.64%"}, {"ticker": "PM", "name": "Philip Morris International Inc.", "change": "-5.28%"}, {"ticker": "CLX", "name": "The Clorox Company", "change": "-5.36%"}, {"ticker": "DELL", "name": "Dell Technologies Inc.", "change": "-5.20%"}, {"ticker": "UNIRF", "name": "Unibail-Rodamco-Westfield", "change": "-5.16%"}, {"ticker": "DOOO", "name": "BRP Inc.", "change": "-5.08%"}, {"ticker": "TGT", "name": "Target Corporation", "change": "-4.98%"}, {"ticker": "SHOO", "name": "Steven Madden, Ltd.", "change": "-5.02%"}, {"ticker": "SGRY", "name": "Surgery Partners, Inc.", "change": "-5.00%"}, {"ticker": "GATX", "name": "GATX Corporation", "change": "-4.93%"}, {"ticker": "NWL", "name": "Newell Brands Inc.", "change": "-4.84%"}]}