{"timestamp": "Tue Sep 13 16:16:11 2022", "loosers": [{"ticker": "WXXWY", "name": "WuXi Biologics (Cayman) Inc.", "change": "-19.40%"}, {"ticker": "OCDGF", "name": "Ocado Group plc", "change": "-16.07%"}, {"ticker": "BRZE", "name": "Braze, Inc.", "change": "-15.47%"}, {"ticker": "OCDDY", "name": "Ocado Group plc", "change": "-14.69%"}, {"ticker": "RLAY", "name": "Relay Therapeutics, Inc.", "change": "-14.74%"}, {"ticker": "SYNH", "name": "Syneos Health, Inc.", "change": "-12.51%"}, {"ticker": "CVNA", "name": "Carvana Co.", "change": "-12.70%"}, {"ticker": "PTON", "name": "Peloton Interactive, Inc.", "change": "-11.95%"}, {"ticker": "W", "name": "Wayfair Inc.", "change": "-11.01%"}, {"ticker": "U", "name": "Unity Software Inc.", "change": "-10.77%"}, {"ticker": "FATE", "name": "Fate Therapeutics, Inc.", "change": "-10.82%"}, {"ticker": "MSTR", "name": "MicroStrategy Incorporated", "change": "-10.29%"}, {"ticker": "TXG", "name": "10x Genomics, Inc.", "change": "-10.04%"}, {"ticker": "ASAN", "name": "Asana, Inc.", "change": "-9.99%"}, {"ticker": "NET", "name": "Cloudflare, Inc.", "change": "-10.05%"}, {"ticker": "ARWR", "name": "Arrowhead Pharmaceuticals, Inc.", "change": "-9.52%"}, {"ticker": "TWST", "name": "Twist Bioscience Corporation", "change": "-9.30%"}, {"ticker": "ZLNDY", "name": "Zalando SE", "change": "-9.36%"}, {"ticker": "PAYO", "name": "Payoneer Global Inc.", "change": "-9.45%"}, {"ticker": "ADYEY", "name": "Adyen N.V.", "change": "-9.20%"}, {"ticker": "AKBTY", "name": "Akbank T.A.S.", "change": "-8.92%"}, {"ticker": "PAX", "name": "Patria Investments Limited", "change": "-8.81%"}, {"ticker": "UPST", "name": "Upstart Holdings, Inc.", "change": "-8.21%"}, {"ticker": "NVAX", "name": "Novavax, Inc.", "change": "-8.40%"}, {"ticker": "AFRM", "name": "Affirm Holdings, Inc.", "change": "-8.62%"}]}