{"timestamp": "Fri Jan 14 17:18:34 2022", "loosers": [{"ticker": "DDL", "name": "Dingdong (Cayman) Limited", "change": "-14.96%"}, {"ticker": "ECIFY", "name": "Electricit\u00e9 de France S.A.", "change": "-13.91%"}, {"ticker": "VORB", "name": "Virgin Orbit Holdings, Inc.", "change": "-13.09%"}, {"ticker": "CVAC", "name": "CureVac N.V.", "change": "-12.45%"}, {"ticker": "RVLV", "name": "Revolve Group, Inc.", "change": "-10.71%"}, {"ticker": "EGRNF", "name": "China Evergrande Group", "change": "-4.55%"}, {"ticker": "SAM", "name": "The Boston Beer Company, Inc.", "change": "-9.75%"}, {"ticker": "AGL", "name": "agilon health, inc.", "change": "-9.02%"}, {"ticker": "ONON", "name": "On Holding AG", "change": "-9.07%"}, {"ticker": "DOCN", "name": "DigitalOcean Holdings, Inc.", "change": "-8.63%"}, {"ticker": "SKIN", "name": "The Beauty Health Company", "change": "-8.26%"}, {"ticker": "BYND", "name": "Beyond Meat, Inc.", "change": "-7.99%"}, {"ticker": "ONEM", "name": "1Life Healthcare, Inc.", "change": "-7.96%"}, {"ticker": "CRNC", "name": "Cerence Inc.", "change": "-7.70%"}, {"ticker": "SWAV", "name": "ShockWave Medical, Inc.", "change": "-7.64%"}, {"ticker": "FQVLF", "name": "First Quantum Minerals Ltd.", "change": "-7.27%"}, {"ticker": "PACB", "name": "Pacific Biosciences of California, Inc.", "change": "-7.27%"}, {"ticker": "DNA", "name": "Ginkgo Bioworks Holdings, Inc.", "change": "-7.00%"}, {"ticker": "JWN", "name": "Nordstrom, Inc.", "change": "-6.82%"}, {"ticker": "CCXI", "name": "ChemoCentryx, Inc.", "change": "-6.98%"}, {"ticker": "OSH", "name": "Oak Street Health, Inc.", "change": "-6.79%"}, {"ticker": "ME", "name": "23andMe Holding Co.", "change": "-6.28%"}, {"ticker": "CDLX", "name": "Cardlytics, Inc.", "change": "-6.68%"}, {"ticker": "MQ", "name": "Marqeta, Inc.", "change": "-6.49%"}, {"ticker": "ABCL", "name": "AbCellera Biologics Inc.", "change": "-6.35%"}]}