{"timestamp": "Fri May 12 14:08:00 2023", "loosers": [{"ticker": "JBSAY", "name": "JBS S.A.", "change": "-10.20%"}, {"ticker": "XPEV", "name": "XPeng Inc.", "change": "-9.22%"}, {"ticker": "SLRN", "name": "Acelyrin, Inc.", "change": "-5.70%"}, {"ticker": "ZLAB", "name": "Zai Lab Limited", "change": "-6.75%"}, {"ticker": "GEN", "name": "Gen Digital Inc.", "change": "-6.26%"}, {"ticker": "W", "name": "Wayfair Inc.", "change": "-6.26%"}, {"ticker": "DNA", "name": "Ginkgo Bioworks Holdings, Inc.", "change": "-5.26%"}, {"ticker": "AGTI", "name": "Agiliti, Inc.", "change": "-5.78%"}, {"ticker": "NIO", "name": "NIO Inc.", "change": "-5.50%"}, {"ticker": "ACLX", "name": "Arcellx, Inc.", "change": "-5.32%"}, {"ticker": "BILI", "name": "Bilibili Inc.", "change": "-5.18%"}, {"ticker": "YETI", "name": "YETI Holdings, Inc.", "change": "-5.08%"}, {"ticker": "U", "name": "Unity Software Inc.", "change": "-5.18%"}, {"ticker": "NEO", "name": "NeoGenomics, Inc.", "change": "-5.09%"}, {"ticker": "AFRM", "name": "Affirm Holdings, Inc.", "change": "-5.07%"}, {"ticker": "TGTX", "name": "TG Therapeutics, Inc.", "change": "-4.92%"}, {"ticker": "ARWR", "name": "Arrowhead Pharmaceuticals, Inc.", "change": "-4.57%"}, {"ticker": "GDS", "name": "GDS Holdings Limited", "change": "-4.40%"}, {"ticker": "TKC", "name": "Turkcell Iletisim Hizmetleri A.S.", "change": "-4.40%"}, {"ticker": "RIVN", "name": "Rivian Automotive, Inc.", "change": "-4.37%"}, {"ticker": "BAK", "name": "Braskem S.A.", "change": "-4.37%"}, {"ticker": "TCCPY", "name": "TechnoPro Holdings, Inc.", "change": "-4.32%"}, {"ticker": "JD", "name": "JD.com, Inc.", "change": "-4.33%"}, {"ticker": "TWLO", "name": "Twilio Inc.", "change": "-4.42%"}, {"ticker": "CTLT", "name": "Catalent, Inc.", "change": "-3.95%"}]}