{"timestamp": "Tue Aug  2 18:14:01 2022", "loosers": [{"ticker": "QRTEB", "name": "Qurate Retail, Inc.", "change": "-19.23%"}, {"ticker": "SYNH", "name": "Syneos Health, Inc.", "change": "-17.34%"}, {"ticker": "SYM", "name": "Symbotic Inc.", "change": "-10.72%"}, {"ticker": "WIRE", "name": "Encore Wire Corporation", "change": "-10.75%"}, {"ticker": "TAP", "name": "Molson Coors Beverage Company", "change": "-9.66%"}, {"ticker": "WWD", "name": "Woodward, Inc.", "change": "-9.85%"}, {"ticker": "CACC", "name": "Credit Acceptance Corporation", "change": "-9.05%"}, {"ticker": "ARNC", "name": "Arconic Corporation", "change": "-8.48%"}, {"ticker": "SEE", "name": "Sealed Air Corporation", "change": "-8.27%"}, {"ticker": "MATX", "name": "Matson, Inc.", "change": "-7.73%"}, {"ticker": "CAR", "name": "Avis Budget Group, Inc.", "change": "-6.90%"}, {"ticker": "KMPR", "name": "Kemper Corporation", "change": "-7.34%"}, {"ticker": "INCY", "name": "Incyte Corporation", "change": "-6.68%"}, {"ticker": "BTDPY", "name": "Barratt Developments plc", "change": "-6.71%"}, {"ticker": "LUNMF", "name": "Lundin Mining Corporation", "change": "-6.66%"}, {"ticker": "SGRY", "name": "Surgery Partners, Inc.", "change": "-6.64%"}, {"ticker": "ZBRA", "name": "Zebra Technologies Corporation", "change": "-6.46%"}, {"ticker": "KD", "name": "Kyndryl Holdings, Inc.", "change": "-6.06%"}, {"ticker": "ATKR", "name": "Atkore Inc.", "change": "-6.13%"}, {"ticker": "JBLU", "name": "JetBlue Airways Corporation", "change": "-6.11%"}, {"ticker": "KIGRY", "name": "KION GROUP AG", "change": "-5.98%"}, {"ticker": "ABR", "name": "Arbor Realty Trust, Inc.", "change": "-5.95%"}, {"ticker": "BERY", "name": "Berry Global Group, Inc.", "change": "-5.82%"}, {"ticker": "CS", "name": "Credit Suisse Group AG", "change": "-5.81%"}, {"ticker": "WETG", "name": "WeTrade Group, Inc.", "change": "-5.71%"}]}