{"timestamp": "Thu May 26 15:13:09 2022", "loosers": [{"ticker": "KREVF", "name": "Keppel REIT", "change": "-34.94%"}, {"ticker": "NTNX", "name": "Nutanix, Inc.", "change": "-27.12%"}, {"ticker": "VSAT", "name": "Viasat, Inc.", "change": "-12.82%"}, {"ticker": "SNOW", "name": "Snowflake Inc.", "change": "-7.08%"}, {"ticker": "MOH", "name": "Molina Healthcare, Inc.", "change": "-6.79%"}, {"ticker": "KHC", "name": "The Kraft Heinz Company", "change": "-6.22%"}, {"ticker": "GLNG", "name": "Golar LNG Limited", "change": "-4.30%"}, {"ticker": "MDT", "name": "Medtronic plc", "change": "-4.15%"}, {"ticker": "CNC", "name": "Centene Corporation", "change": "-3.90%"}, {"ticker": "LGF-B", "name": "Lions Gate Entertainment Corp.", "change": "-2.89%"}, {"ticker": "LGF-A", "name": "Lions Gate Entertainment Corp.", "change": "-3.28%"}, {"ticker": "FNMAS", "name": "Federal National Mortgage Association", "change": "-3.12%"}, {"ticker": "ZLAB", "name": "Zai Lab Limited", "change": "-3.11%"}, {"ticker": "NGG", "name": "National Grid plc", "change": "-3.05%"}, {"ticker": "ADC", "name": "Agree Realty Corporation", "change": "-3.09%"}, {"ticker": "FMCKJ", "name": "Federal Home Loan Mortgage Corporation", "change": "-3.03%"}, {"ticker": "CIMEF", "name": "CIMC Enric Holdings Limited", "change": "-2.80%"}, {"ticker": "CIG-C", "name": "Companhia Energ\u00e9tica de Minas Gerais", "change": "-2.74%"}, {"ticker": "FSUGY", "name": "Fortescue Metals Group Limited", "change": "-2.58%"}]}