{"timestamp": "Fri Aug 12 14:10:50 2022", "loosers": [{"ticker": "CERT", "name": "Certara, Inc.", "change": "-14.09%"}, {"ticker": "KNRRY", "name": "Knorr-Bremse Aktiengesellschaft", "change": "-11.93%"}, {"ticker": "MCW", "name": "Mister Car Wash, Inc.", "change": "-12.42%"}, {"ticker": "AGL", "name": "agilon health, inc.", "change": "-10.68%"}, {"ticker": "YMM", "name": "Full Truck Alliance Co. Ltd.", "change": "-9.29%"}, {"ticker": "ILMN", "name": "Illumina, Inc.", "change": "-8.99%"}, {"ticker": "ZIM", "name": "ZIM Integrated Shipping Services Ltd.", "change": "-7.57%"}, {"ticker": "JKS", "name": "JinkoSolar Holding Co., Ltd.", "change": "-7.00%"}, {"ticker": "LU", "name": "Lufax Holding Ltd", "change": "-6.66%"}, {"ticker": "AMKBY", "name": "A.P. M\u00f8ller - M\u00e6rsk A/S", "change": "-5.69%"}, {"ticker": "NTCO", "name": "Natura &Co Holding S.A.", "change": "-5.99%"}, {"ticker": "HPK", "name": "HighPeak Energy, Inc.", "change": "-4.45%"}, {"ticker": "GXO", "name": "GXO Logistics, Inc.", "change": "-5.30%"}, {"ticker": "BVNRY", "name": "Bavarian Nordic A/S", "change": "-4.97%"}, {"ticker": "VET", "name": "Vermilion Energy Inc.", "change": "-4.81%"}, {"ticker": "INSP", "name": "Inspire Medical Systems, Inc.", "change": "-4.82%"}, {"ticker": "VIPS", "name": "Vipshop Holdings Limited", "change": "-4.47%"}, {"ticker": "DITHF", "name": "DS Smith Plc", "change": "-4.41%"}, {"ticker": "AMTD", "name": "AMTD IDEA Group", "change": "-3.90%"}, {"ticker": "IDCBF", "name": "Industrial & Commercial Bank of China Ltd.", "change": "-4.17%"}, {"ticker": "DQ", "name": "Daqo New Energy Corp.", "change": "-4.06%"}, {"ticker": "SHI", "name": "Sinopec Shanghai Petrochemical Company Limited", "change": "-3.85%"}, {"ticker": "TME", "name": "Tencent Music Entertainment Group", "change": "-4.20%"}, {"ticker": "LFC", "name": "China Life Insurance Company Limited", "change": "-3.66%"}, {"ticker": "ACH", "name": "Aluminum Corporation of China Limited", "change": "-3.68%"}]}