{"timestamp": "Fri Jan  6 18:11:43 2023", "loosers": [{"ticker": "HKD", "name": "AMTD Digital Inc.", "change": "-24.91%"}, {"ticker": "PBMRF", "name": "PT Bumi Resources Tbk", "change": "-16.00%"}, {"ticker": "XPEV", "name": "XPeng Inc.", "change": "-15.84%"}, {"ticker": "IQ", "name": "iQIYI, Inc.", "change": "-14.72%"}, {"ticker": "DADA", "name": "Dada Nexus Limited", "change": "-11.11%"}, {"ticker": "LI", "name": "Li Auto Inc.", "change": "-10.57%"}, {"ticker": "DAVE", "name": "Dave Inc.", "change": "-8.97%"}, {"ticker": "TRN", "name": "Trinity Industries, Inc.", "change": "-7.37%"}, {"ticker": "WAT", "name": "Waters Corporation", "change": "-7.09%"}, {"ticker": "BRKR", "name": "Bruker Corporation", "change": "-6.87%"}, {"ticker": "INSM", "name": "Insmed Incorporated", "change": "-6.69%"}, {"ticker": "PTKFF", "name": "PT Kalbe Farma Tbk.", "change": "-6.83%"}, {"ticker": "FROG", "name": "JFrog Ltd.", "change": "-6.87%"}, {"ticker": "NIO", "name": "NIO Inc.", "change": "-6.58%"}, {"ticker": "SAPMD", "name": "Saipem SpA", "change": "-6.38%"}, {"ticker": "BAX", "name": "Baxter International Inc.", "change": "-5.48%"}, {"ticker": "PWSC", "name": "PowerSchool Holdings, Inc.", "change": "-5.00%"}, {"ticker": "DOCS", "name": "Doximity, Inc.", "change": "-4.90%"}, {"ticker": "MTD", "name": "Mettler-Toledo International Inc.", "change": "-4.49%"}, {"ticker": "PKI", "name": "PerkinElmer, Inc.", "change": "-4.65%"}, {"ticker": "RGEN", "name": "Repligen Corporation", "change": "-4.77%"}, {"ticker": "MPNGY", "name": "Meituan", "change": "-4.57%"}, {"ticker": "A", "name": "Agilent Technologies, Inc.", "change": "-4.41%"}, {"ticker": "NVCR", "name": "NovoCure Limited", "change": "-4.39%"}, {"ticker": "DNA", "name": "Ginkgo Bioworks Holdings, Inc.", "change": "-4.46%"}]}