{"timestamp": "Wed Feb 15 15:10:34 2023", "loosers": [{"ticker": "DVN", "name": "Devon Energy Corporation", "change": "-11.76%"}, {"ticker": "HL", "name": "Hecla Mining Company", "change": "-9.47%"}, {"ticker": "BCS", "name": "Barclays PLC", "change": "-9.49%"}, {"ticker": "AKAM", "name": "Akamai Technologies, Inc.", "change": "-8.53%"}, {"ticker": "AU", "name": "AngloGold Ashanti Limited", "change": "-7.13%"}, {"ticker": "CORT", "name": "Corcept Therapeutics Incorporated", "change": "-7.55%"}, {"ticker": "KB", "name": "KB Financial Group Inc.", "change": "-6.82%"}, {"ticker": "LAD", "name": "Lithia Motors, Inc.", "change": "-5.80%"}, {"ticker": "PILBF", "name": "Pilbara Minerals Limited", "change": "-5.44%"}, {"ticker": "SCI", "name": "Service Corporation International", "change": "-6.71%"}, {"ticker": "TSM", "name": "Taiwan Semiconductor Manufacturing Company Limited", "change": "-6.67%"}, {"ticker": "MEDP", "name": "Medpace Holdings, Inc.", "change": "-7.08%"}, {"ticker": "PCCYF", "name": "PetroChina Company Limited", "change": "-6.14%"}, {"ticker": "ANGPY", "name": "Anglo American Platinum Limited", "change": "-6.12%"}, {"ticker": "DADA", "name": "Dada Nexus Limited", "change": "-6.05%"}, {"ticker": "TIGO", "name": "Millicom International Cellular S.A.", "change": "-5.85%"}, {"ticker": "DY", "name": "Dycom Industries, Inc.", "change": "-5.16%"}, {"ticker": "CPE", "name": "Callon Petroleum Company", "change": "-5.88%"}, {"ticker": "SHG", "name": "Shinhan Financial Group Co., Ltd.", "change": "-5.37%"}, {"ticker": "GFS", "name": "GLOBALFOUNDRIES Inc.", "change": "-4.94%"}, {"ticker": "IMPUY", "name": "Impala Platinum Holdings Limited", "change": "-5.40%"}, {"ticker": "GELYF", "name": "Geely Automobile Holdings Limited", "change": "-5.19%"}, {"ticker": "KEP", "name": "Korea Electric Power Corporation", "change": "-5.09%"}, {"ticker": "GLCNF", "name": "Glencore plc", "change": "-5.02%"}, {"ticker": "PSN", "name": "Parsons Corporation", "change": "-4.81%"}]}