{"timestamp": "Thu Jan 26 17:08:48 2023", "loosers": [{"ticker": "RADLY", "name": "Raia Drogasil S.A.", "change": "-20.95%"}, {"ticker": "PLXS", "name": "Plexus Corp.", "change": "-15.24%"}, {"ticker": "VIRT", "name": "Virtu Financial, Inc.", "change": "-7.44%"}, {"ticker": "SHLS", "name": "Shoals Technologies Group, Inc.", "change": "-8.36%"}, {"ticker": "SHW", "name": "The Sherwin-Williams Company", "change": "-7.68%"}, {"ticker": "CLBK", "name": "Columbia Financial, Inc.", "change": "-7.31%"}, {"ticker": "ATLKY", "name": "Atlas Copco AB", "change": "-7.11%"}, {"ticker": "VSAT", "name": "Viasat, Inc.", "change": "-7.07%"}, {"ticker": "PLUG", "name": "Plug Power Inc.", "change": "-6.92%"}, {"ticker": "SNX", "name": "TD SYNNEX Corporation", "change": "-6.40%"}, {"ticker": "ARRY", "name": "Array Technologies, Inc.", "change": "-6.29%"}, {"ticker": "SANM", "name": "Sanmina Corporation", "change": "-6.07%"}, {"ticker": "IMPUY", "name": "Impala Platinum Holdings Limited", "change": "-5.89%"}, {"ticker": "DEO", "name": "Diageo plc", "change": "-5.68%"}, {"ticker": "ATAT", "name": "Atour Lifestyle Holdings Limited", "change": "-5.68%"}, {"ticker": "WYNMY", "name": "Wynn Macau, Limited", "change": "-5.52%"}, {"ticker": "XRX", "name": "Xerox Holdings Corporation", "change": "-5.25%"}, {"ticker": "MKC", "name": "McCormick & Company, Incorporated", "change": "-5.42%"}, {"ticker": "BOWL", "name": "Bowlero Corp.", "change": "-5.34%"}, {"ticker": "TIGO", "name": "Millicom International Cellular S.A.", "change": "-5.23%"}, {"ticker": "EXP", "name": "Eagle Materials Inc.", "change": "-5.20%"}, {"ticker": "VIR", "name": "Vir Biotechnology, Inc.", "change": "-5.03%"}, {"ticker": "NG", "name": "NovaGold Resources Inc.", "change": "-4.89%"}, {"ticker": "IBM", "name": "International Business Machines Corporation", "change": "-4.77%"}, {"ticker": "LUV", "name": "Southwest Airlines Co.", "change": "-4.60%"}]}