{"timestamp": "Mon Aug 15 14:13:12 2022", "loosers": [{"ticker": "TRQ", "name": "Turquoise Hill Resources Ltd.", "change": "-11.83%"}, {"ticker": "NEX", "name": "NexTier Oilfield Solutions Inc.", "change": "-9.80%"}, {"ticker": "PTEN", "name": "Patterson-UTI Energy, Inc.", "change": "-9.42%"}, {"ticker": "GOGL", "name": "Golden Ocean Group Limited", "change": "-9.41%"}, {"ticker": "ME", "name": "23andMe Holding Co.", "change": "-8.79%"}, {"ticker": "VAL", "name": "Valaris Limited", "change": "-8.99%"}, {"ticker": "KOS", "name": "Kosmos Energy Ltd.", "change": "-9.31%"}, {"ticker": "RIG", "name": "Transocean Ltd.", "change": "-8.84%"}, {"ticker": "HPK", "name": "HighPeak Energy, Inc.", "change": "-8.16%"}, {"ticker": "HP", "name": "Helmerich & Payne, Inc.", "change": "-8.72%"}, {"ticker": "SM", "name": "SM Energy Company", "change": "-8.44%"}, {"ticker": "NE", "name": "Noble Corporation", "change": "-8.28%"}, {"ticker": "LBRT", "name": "Liberty Energy Inc.", "change": "-8.01%"}, {"ticker": "CRK", "name": "Comstock Resources, Inc.", "change": "-7.93%"}, {"ticker": "CVI", "name": "CVR Energy, Inc.", "change": "-7.80%"}, {"ticker": "SWN", "name": "Southwestern Energy Company", "change": "-7.79%"}, {"ticker": "NOG", "name": "Northern Oil and Gas, Inc.", "change": "-7.64%"}, {"ticker": "MEGEF", "name": "MEG Energy Corp.", "change": "-7.54%"}, {"ticker": "ROOT", "name": "Root, Inc.", "change": "-5.85%"}, {"ticker": "VET", "name": "Vermilion Energy Inc.", "change": "-7.34%"}, {"ticker": "CPE", "name": "Callon Petroleum Company", "change": "-7.81%"}, {"ticker": "CRGY", "name": "Crescent Energy Company", "change": "-7.18%"}, {"ticker": "EQT", "name": "EQT Corporation", "change": "-6.99%"}, {"ticker": "AR", "name": "Antero Resources Corporation", "change": "-7.07%"}, {"ticker": "PBF", "name": "PBF Energy Inc.", "change": "-7.60%"}]}