{"timestamp": "Thu Feb  2 18:12:21 2023", "loosers": [{"ticker": "HBI", "name": "Hanesbrands Inc.", "change": "-24.51%"}, {"ticker": "GOOS", "name": "Canada Goose Holdings Inc.", "change": "-20.55%"}, {"ticker": "SLM", "name": "SLM Corporation", "change": "-17.45%"}, {"ticker": "WMS", "name": "Advanced Drainage Systems, Inc.", "change": "-15.65%"}, {"ticker": "CHX", "name": "ChampionX Corporation", "change": "-10.71%"}, {"ticker": "SIRI", "name": "Sirius XM Holdings Inc.", "change": "-9.22%"}, {"ticker": "PBH", "name": "Prestige Consumer Healthcare Inc.", "change": "-9.16%"}, {"ticker": "ROIV", "name": "Roivant Sciences Ltd.", "change": "-8.37%"}, {"ticker": "CNHI", "name": "CNH Industrial N.V.", "change": "-8.52%"}, {"ticker": "ARRY", "name": "Array Technologies, Inc.", "change": "-7.45%"}, {"ticker": "MUSA", "name": "Murphy USA Inc.", "change": "-6.57%"}, {"ticker": "APD", "name": "Air Products and Chemicals, Inc.", "change": "-6.54%"}, {"ticker": "DB", "name": "Deutsche Bank Aktiengesellschaft", "change": "-6.41%"}, {"ticker": "MKL", "name": "Markel Corporation", "change": "-6.26%"}, {"ticker": "AFL", "name": "Aflac Incorporated", "change": "-6.13%"}, {"ticker": "FLNC", "name": "Fluence Energy, Inc.", "change": "-5.50%"}, {"ticker": "QFIN", "name": "360 DigiTech, Inc.", "change": "-5.86%"}, {"ticker": "LSXMK", "name": "The Liberty SiriusXM Group", "change": "-5.62%"}, {"ticker": "LLY", "name": "Eli Lilly and Company", "change": "-5.55%"}, {"ticker": "LSXMA", "name": "The Liberty SiriusXM Group", "change": "-5.56%"}, {"ticker": "LSPD", "name": "Lightspeed Commerce Inc.", "change": "-5.64%"}, {"ticker": "CIG-C", "name": "Companhia Energ\u00e9tica de Minas Gerais", "change": "-5.44%"}, {"ticker": "NVO", "name": "Novo Nordisk A/S", "change": "-5.47%"}, {"ticker": "DE", "name": "Deere & Company", "change": "-5.35%"}, {"ticker": "ING", "name": "ING Groep N.V.", "change": "-5.40%"}]}