{"timestamp": "Wed Feb  1 17:09:14 2023", "loosers": [{"ticker": "WRK", "name": "WestRock Company", "change": "-14.68%"}, {"ticker": "SNAP", "name": "Snap Inc.", "change": "-14.14%"}, {"ticker": "EA", "name": "Electronic Arts Inc.", "change": "-12.17%"}, {"ticker": "AKBTY", "name": "Akbank T.A.S.", "change": "-10.34%"}, {"ticker": "MTCH", "name": "Match Group, Inc.", "change": "-9.61%"}, {"ticker": "SOMMY", "name": "Sumitomo Chemical Company, Limited", "change": "-8.62%"}, {"ticker": "LSRCY", "name": "Lasertec Corporation", "change": "-8.50%"}, {"ticker": "TRP", "name": "TC Energy Corporation", "change": "-7.87%"}, {"ticker": "CSCCF", "name": "Capstone Copper Corp.", "change": "-6.84%"}, {"ticker": "JCI", "name": "Johnson Controls International plc", "change": "-6.54%"}, {"ticker": "CPE", "name": "Callon Petroleum Company", "change": "-6.18%"}, {"ticker": "LAC", "name": "Lithium Americas Corp.", "change": "-6.36%"}, {"ticker": "PBF", "name": "PBF Energy Inc.", "change": "-5.95%"}, {"ticker": "VET", "name": "Vermilion Energy Inc.", "change": "-5.61%"}, {"ticker": "SYF", "name": "Synchrony Financial", "change": "-5.79%"}, {"ticker": "BTGOF", "name": "BT Group plc", "change": "-5.70%"}, {"ticker": "CPG", "name": "Crescent Point Energy Corp.", "change": "-5.56%"}, {"ticker": "GME", "name": "GameStop Corp.", "change": "-5.40%"}, {"ticker": "SM", "name": "SM Energy Company", "change": "-5.20%"}, {"ticker": "OVV", "name": "Ovintiv Inc.", "change": "-5.48%"}, {"ticker": "PDCE", "name": "PDC Energy, Inc.", "change": "-5.46%"}, {"ticker": "RES", "name": "RPC, Inc.", "change": "-5.39%"}, {"ticker": "ERF", "name": "Enerplus Corporation", "change": "-5.24%"}, {"ticker": "TPL", "name": "Texas Pacific Land Corporation", "change": "-5.25%"}, {"ticker": "IEX", "name": "IDEX Corporation", "change": "-5.17%"}]}